fcm_mpmath.py
fcm_mpmath-0.1.3.dist-info/LICENSE
fcm_mpmath-0.1.3.dist-info/METADATA
fcm_mpmath-0.1.3.dist-info/WHEEL
fcm_mpmath-0.1.3.dist-info/RECORD
