Metadata-Version: 2.1
Name: fcm-mpmath
Version: 0.1.3
Summary: 
Author: Anderson Alencar
Author-email: alencarbarros@protonmail.com
Requires-Python: >=3.10,<4.0
Classifier: Programming Language :: Python :: 3
Classifier: Programming Language :: Python :: 3.10
Classifier: Programming Language :: Python :: 3.11
Requires-Dist: mpmath (>=1.3.0,<2.0.0)
Requires-Dist: numpy (>=1.24.3,<2.0.0)
Requires-Dist: pytest (>=7.3.1,<8.0.0)
